.VERSION
AUTHORS.rst
CONTRIBUTING.rst
HISTORY.rst
LICENSE
MANIFEST.in
Pipfile
Pipfile.lock
README.rst
USAGE.rst
dev-requirements.txt
requirements.txt
setup.cfg
setup.py
_CI/__init__.py
_CI/configuration/__init__.py
_CI/configuration/configuration.py
_CI/library/__init__.py
_CI/library/core_library.py
_CI/library/patch.py
_CI/scripts/__init__.py
_CI/scripts/_initialize_template.py
_CI/scripts/bootstrap.py
_CI/scripts/build.py
_CI/scripts/document.py
_CI/scripts/graph.py
_CI/scripts/lint.py
_CI/scripts/lock.py
_CI/scripts/reset.py
_CI/scripts/tag.py
_CI/scripts/test.py
_CI/scripts/update.py
_CI/scripts/upload.py
docs/Makefile
docs/authors.rst
docs/conf.py
docs/contributing.rst
docs/history.rst
docs/index.rst
docs/installation.rst
docs/modules.rst
docs/oktalib.entities.rst
docs/oktalib.rst
docs/readme.rst
docs/usage.rst
oktalib/.VERSION
oktalib/AUTHORS.rst
oktalib/CONTRIBUTING.rst
oktalib/HISTORY.rst
oktalib/LICENSE
oktalib/Pipfile
oktalib/Pipfile.lock
oktalib/README.rst
oktalib/USAGE.rst
oktalib/__init__.py
oktalib/_version.py
oktalib/dev-requirements.txt
oktalib/oktalib.py
oktalib/oktalibexceptions.py
oktalib/requirements.txt
oktalib.egg-info/PKG-INFO
oktalib.egg-info/SOURCES.txt
oktalib.egg-info/dependency_links.txt
oktalib.egg-info/not-zip-safe
oktalib.egg-info/requires.txt
oktalib.egg-info/top_level.txt
oktalib/entities/__init__.py
oktalib/entities/core.py
oktalib/entities/entities.py
tests/test_oktalib.py