Metadata-Version: 2.1
Name: oktalib
Version: 2.1.0
Summary: A library to interface with okta through it's restful api
Home-page: https://github.com/schubergphilis/oktalib.git
Author: Costas Tyfoxylos
Author-email: ctyfoxylos@schubergphilis.com
License: MIT
Keywords: oktalib okta api python rest
Classifier: Development Status :: 4 - Beta
Classifier: Intended Audience :: Developers
Classifier: License :: OSI Approved :: MIT License
Classifier: Natural Language :: English
Classifier: Programming Language :: Python :: 3.9
License-File: LICENSE
License-File: AUTHORS.rst
Requires-Dist: requests>=2.31.0; python_version >= "3.7"
Requires-Dist: dateutils>=0.6.12
Requires-Dist: backoff>=1.11.1; python_version >= "2.7" and python_version not in "3.0, 3.1, 3.2, 3.3, 3.4"
Requires-Dist: cachetools>=5.3.2; python_version >= "3.7"
